rapidhash-0.1.0.dist-info/METADATA
rapidhash-0.1.0.dist-info/WHEEL
rapidhash-0.1.0.dist-info/licenses/LICENSE
rapidhash.libs/libgcc_s-1e52349c.so.1
rapidhash/_core.pyi
rapidhash/__init__.py
rapidhash/py.typed
rapidhash/_core.cpython-313t-x86_64-linux-musl.so
rapidhash-0.1.0.dist-info/RECORD
