Metadata-Version: 2.4
Name: rapidhash
Version: 0.1.0
License-File: LICENSE
Summary: Very fast, high quality, platform-independent hashing algorithm.
Author-email: Ryan Aoi <163698864+ryan-aoi@users.noreply.github.com>
Requires-Python: >=3.10
